LICENSE
setup.py
django_virtualssi.egg-info/PKG-INFO
django_virtualssi.egg-info/SOURCES.txt
django_virtualssi.egg-info/dependency_links.txt
django_virtualssi.egg-info/not-zip-safe
django_virtualssi.egg-info/top_level.txt
virtualssi/__init__.py
virtualssi/templatetags/__init__.py
virtualssi/templatetags/vssi.py