Metadata-Version: 1.0
Name: django-virtualssi
Version: 1.0.1
Summary: Simulate Apache virtual server-side includes.
Home-page: http://pypi.python.org/pypi/django-virtualssi
Author: Tamas Kemenczy
Author-email: tamas.kemenczy@gmail.com
License: BSD
Platform: UNKNOWN
Classifier: Development Status :: 5 - Production/Stable
Classifier: Environment :: Web Environment
Classifier: Framework :: Django
Classifier: Intended Audience :: Developers
Classifier: License :: OSI Approved :: BSD License
Classifier: Operating System :: OS Independent
Classifier: Programming Language :: Python
